django_dropboxchooser_field3-0.0.5.dist-info/DESCRIPTION.rst
django_dropboxchooser_field3-0.0.5.dist-info/METADATA
django_dropboxchooser_field3-0.0.5.dist-info/RECORD
django_dropboxchooser_field3-0.0.5.dist-info/WHEEL
django_dropboxchooser_field3-0.0.5.dist-info/metadata.json
django_dropboxchooser_field3-0.0.5.dist-info/top_level.txt
dropboxchooser_field/__init__.py
dropboxchooser_field/fields.py
dropboxchooser_field/widgets.py
dropboxchooser_field/static/js/dropboxchooser_field/chooser.js
