Metadata-Version: 2.0
Name: django-dropboxchooser-field3
Version: 0.0.5
Summary: Dropbox chooser field for django
Home-page: https://github.com/bogdal/django-dropboxchooser-field
Author: Adam Bogdal
Author-email: adam@bogdal.pl
License: UNKNOWN
Platform: UNKNOWN
Classifier: Development Status :: 4 - Beta
Classifier: Environment :: Web Environment
Classifier: Framework :: Django
Classifier: Intended Audience :: Developers
Classifier: License :: OSI Approved :: BSD License
Classifier: Operating System :: OS Independent
Classifier: Programming Language :: Python
Classifier: Topic :: Software Development :: Libraries :: Python Modules
Classifier: Topic :: Utilities
Requires-Dist: requests
